pyflic/__init__.py
pyflic/asyncio.py
pyflic-2.0.4.dist-info/LICENSE
pyflic-2.0.4.dist-info/METADATA
pyflic-2.0.4.dist-info/WHEEL
pyflic-2.0.4.dist-info/top_level.txt
pyflic-2.0.4.dist-info/RECORD
