Metadata-Version: 2.1
Name: pyflic
Version: 2.0.4
Summary: Python library to connect to and interact with Flic buttons.
Home-page: https://github.com/soldag/pyflic
Author: soldag
Author-email: soeren_oldag@freenet.de
License: MIT
Platform: UNKNOWN
